datetime_iso_format_sort/__init__.py
datetime_iso_format_sort/main.py
datetime_iso_format_sort-0.1.0.dist-info/METADATA
datetime_iso_format_sort-0.1.0.dist-info/WHEEL
datetime_iso_format_sort-0.1.0.dist-info/top_level.txt
datetime_iso_format_sort-0.1.0.dist-info/RECORD
