Metadata-Version: 2.1
Name: datetime-iso-format-sort
Version: 0.1.0
Summary: Datetime iso format sort
Author: Author
License: MIT
